shrinkprompt/__init__.py
shrinkprompt/cli.py
shrinkprompt/compressors/__init__.py
shrinkprompt/compressors/data/synonym_graph.json
shrinkprompt/compressors/step1_normalize.py
shrinkprompt/compressors/step2_mass_removal.py
shrinkprompt/compressors/step3_abbreviate_symbolize.py
shrinkprompt/compressors/step4_smart_context.py
shrinkprompt/compressors/step5_token_optimize.py
shrinkprompt/compressors/step6_advanced_optimization.py
shrinkprompt/compressors/step7_synonym_optimize.py
shrinkprompt/core.py
shrink_prompt-1.0.0.dist-info/METADATA
shrink_prompt-1.0.0.dist-info/WHEEL
shrink_prompt-1.0.0.dist-info/entry_points.txt
shrink_prompt-1.0.0.dist-info/RECORD
