Metadata-Version: 2.3
Name: shrink-prompt
Version: 1.0.0
Summary: Lightning-fast LLM prompt compression with 30-70% token reduction. Domain-specific rules for legal, medical, technical content. Sub-20ms processing, zero external calls.
License: MIT
Keywords: llm,prompt,compression,tokens,openai,cost-optimization,nlp
Author: ShrinkPrompt Contributors
Author-email: shrink-prompt@example.com
Requires-Python: >=3.8,<4.0
Classifier: Development Status :: 5 - Production/Stable
Classifier: Intended Audience :: Developers
Classifier: Intended Audience :: Science/Research
Classifier: License :: OSI Approved :: MIT License
Classifier: Operating System :: OS Independent
Classifier: Programming Language :: Python :: 3
Classifier: Programming Language :: Python :: 3.8
Classifier: Programming Language :: Python :: 3.9
Classifier: Programming Language :: Python :: 3.10
Classifier: Programming Language :: Python :: 3.11
Classifier: Programming Language :: Python :: 3.12
Classifier: Programming Language :: Python :: 3.13
Classifier: Topic :: Scientific/Engineering :: Artificial Intelligence
Classifier: Topic :: Software Development :: Libraries :: Python Modules
Classifier: Topic :: Text Processing :: Linguistic
Requires-Dist: tiktoken (>=0.5.0)
Project-URL: Bug Tracker, https://github.com/yourusername/shrink-prompt/issues
Project-URL: Changelog, https://github.com/yourusername/shrink-prompt/blob/main/CHANGELOG.md
Project-URL: Documentation, https://github.com/yourusername/shrink-prompt
Project-URL: Discussions, https://github.com/yourusername/shrink-prompt/discussions
Project-URL: Homepage, https://github.com/yourusername/shrink-prompt
Project-URL: Repository, https://github.com/yourusername/shrink-prompt
